{
    "trial_type": {
        "Description": "Description for trial_type",
        "HED": {
            "boundary": "(Label/trial_type, Label/boundary)",
            "famous_new": "(Label/trial_type, Label/famous_new)",
            "famous_second_early": "(Label/trial_type, Label/famous_second_early)",
            "famous_second_late": "(Label/trial_type, Label/famous_second_late)",
            "left_nonsym": "(Label/trial_type, Label/left_nonsym)",
            "left_sym": "(Label/trial_type, Label/left_sym)",
            "right_nonsym": "(Label/trial_type, Label/right_nonsym)",
            "right_sym": "(Label/trial_type, Label/right_sym)",
            "scrambled_new": "(Label/trial_type, Label/scrambled_new)",
            "scrambled_second_early": "(Label/trial_type, Label/scrambled_second_early)",
            "scrambled_second_late": "(Label/trial_type, Label/scrambled_second_late)",
            "unfamiliar_new": "(Label/trial_type, Label/unfamiliar_new)",
            "unfamiliar_second_early": "(Label/trial_type, Label/unfamiliar_second_early)",
            "unfamiliar_second_late": "(Label/trial_type, Label/unfamiliar_second_late)"
        },
        "Levels": {
            "boundary": "Here describe column value boundary of column trial_type",
            "famous_new": "Here describe column value famous_new of column trial_type",
            "famous_second_early": "Here describe column value famous_second_early of column trial_type",
            "famous_second_late": "Here describe column value famous_second_late of column trial_type",
            "left_nonsym": "Here describe column value left_nonsym of column trial_type",
            "left_sym": "Here describe column value left_sym of column trial_type",
            "right_nonsym": "Here describe column value right_nonsym of column trial_type",
            "right_sym": "Here describe column value right_sym of column trial_type",
            "scrambled_new": "Here describe column value scrambled_new of column trial_type",
            "scrambled_second_early": "Here describe column value scrambled_second_early of column trial_type",
            "scrambled_second_late": "Here describe column value scrambled_second_late of column trial_type",
            "unfamiliar_new": "Here describe column value unfamiliar_new of column trial_type",
            "unfamiliar_second_early": "Here describe column value unfamiliar_second_early of column trial_type",
            "unfamiliar_second_late": "Here describe column value unfamiliar_second_late of column trial_type"
        }
    },
    "event_order": {
        "Description": "Description for event_order",
        "HED": {
            "0": "(Label/event_order, Label/0)",
            "1": "(Label/event_order, Label/1)",
            "2": "(Label/event_order, Label/2)"
        },
        "Levels": {
            "0": "Here describe column value 0 of column event_order",
            "1": "Here describe column value 1 of column event_order",
            "2": "Here describe column value 2 of column event_order"
        }
    },
    "stim_file": {
        "Description": "Description for stim_file",
        "HED": "(Label/stim_file, Label/#)"
    },
    "trial_dist": {
        "Description": "Description for trial_dist",
        "HED": "(Label/trial_dist, Label/#)"
    },
    "time_dist": {
        "Description": "Description for time_dist",
        "HED": "(Label/time_dist, Label/#)"
    }
}