{
    "Resolution": "2mm isotropic",
    "LabelMap": [
        "Background",
        "Amygdala_centromedial group",
        "Amygdala_laterobasal group",
        "Amygdala_superficial group",
        "Anterior intra-parietal sulcus hIP1",
        "Anterior intra-parietal sulcus hIP2",
        "Anterior intra-parietal sulcus hIP3",
        "Broca's area BA44",
        "Broca's area BA45",
        "Hippocampus cornu ammonis",
        "Hippocampus dentate gyrus",
        "Hippocampus entorhinal cortex",
        "Hippocampus hippocampal-amygdaloid transition area",
        "Hippocampus subiculum",
        "Inferior parietal lobule PF",
        "Inferior parietal lobule PFcm",
        "Inferior parietal lobule PFm",
        "Inferior parietal lobule PFop",
        "Inferior parietal lobule PFt",
        "Inferior parietal lobule PGp",
        "Inferior parietal lobule Pga",
        "Insula Id1",
        "Insula Ig1",
        "Insula Ig2",
        "Lateral geniculate body",
        "Mamillary body",
        "Medial geniculate body",
        "Premotor cortex BA6",
        "Primary auditory cortex TE1.0",
        "Primary auditory cortex TE1.1",
        "Primary auditory cortex TE1.2",
        "Primary motor cortex BA4a",
        "Primary motor cortex BA4p",
        "Primary somatosensory cortex BA1",
        "Primary somatosensory cortex BA2",
        "Primary somatosensory cortex BA3a",
        "Primary somatosensory cortex BA3b",
        "Secondary somatosensory cortex / Parietal operculum OP1",
        "Secondary somatosensory cortex / Parietal operculum OP2",
        "Secondary somatosensory cortex / Parietal operculum OP3",
        "Secondary somatosensory cortex / Parietal operculum OP4",
        "Superior parietal lobule 5Ci",
        "Superior parietal lobule 5L",
        "Superior parietal lobule 5M",
        "Superior parietal lobule 7A",
        "Superior parietal lobule 7M",
        "Superior parietal lobule 7P",
        "Superior parietal lobule 7PC",
        "Visual cortex V1 BA17",
        "Visual cortex V2 BA18",
        "Visual cortex V3V",
        "Visual cortex V4",
        "Visual cortex V5",
        "Acoustic radiation",
        "Callosal body",
        "Cingulum",
        "Corticospinal tract",
        "Fornix",
        "Inferior occipito-frontal fascicle",
        "Optic radiation",
        "Superior longitudinal fascicle",
        "Superior occipito-frontal fascicle",
        "Uncinate fascicle"
    ],
    "hemisphere": {
        "Description": "Hemisphere location of the region",
        "Levels": {
            "L": "Left hemisphere",
            "R": "Right hemisphere",
            "n/a": "Not applicable or bilateral"
        }
    }
}
