{
    "sub-01/dwi/sub-01_dwi.bval": [
        "sub-01/dwi/sub-01_run-1_dwi.nii.gz",
        "sub-01/dwi/sub-01_run-2_dwi.nii.gz"
    ],
    "sub-01/dwi/sub-01_dwi.bvec": [
        "sub-01/dwi/sub-01_run-1_dwi.nii.gz",
        "sub-01/dwi/sub-01_run-2_dwi.nii.gz"
    ],
    "sub-01/dwi/sub-01_run-1_dwi.nii.gz": {
        ".bval": "sub-01/dwi/sub-01_dwi.bval",
        ".bvec": "sub-01/dwi/sub-01_dwi.bvec"
    },
    "sub-01/dwi/sub-01_run-2_dwi.nii.gz": {
        ".bval": "sub-01/dwi/sub-01_dwi.bval",
        ".bvec": "sub-01/dwi/sub-01_dwi.bvec"
    }
}
